[
    {
        "username": "harshika15097",
        "full_name": "Harshika"
    },
    {
        "username": "ranawat_k456",
        "full_name": "Khushi Ranawat"
    },
    {
        "username": "rhythm_._agrawal",
        "full_name": "Rhythm Agrawal"
    },
    {
        "username": "abhinav_pandey.1729",
        "full_name": "Abhinav Pandey"
    },
    {
        "username": "_naman._.sethi",
        "full_name": "Naman Sethi"
    },
    {
        "username": "prashik_ganer",
        "full_name": "Prashik Ganer"
    },
    {
        "username": "mukesh__0136",
        "full_name": "Mu_ke$h...😉"
    },
    {
        "username": "waqar_moid",
        "full_name": "Waqar"
    },
    {
        "username": "sanskrati4635",
        "full_name": "Sanskrati Agarwal"
    },
    {
        "username": "_gauravk04",
        "full_name": "Gaurav"
    },
    {
        "username": "thisisharshpreet",
        "full_name": "Harshpreet Kaur"
    },
    {
        "username": "lasya_siri_g",
        "full_name": "Lasya Siri"
    },
    {
        "username": "nischay2305",
        "full_name": "Nischay Agarwal"
    },
    {
        "username": "shubhhh._._",
        "full_name": "Shubh Tandon"
    },
    {
        "username": "ayush_1565",
        "full_name": "Ayush Inamdar"
    },
    {
        "username": "aer0expert07tr",
        "full_name": "Tanmay Ashish Rajput"
    },
    {
        "username": "jayanth_mattam",
        "full_name": ""
    },
    {
        "username": "_rohit_somani",
        "full_name": "Rohit Somani"
    },
    {
        "username": "ishita_porwal11",
        "full_name": "Ishita Porwal"
    },
    {
        "username": "iitk.raset",
        "full_name": "IITK Rocketry and Space Exploration Team"
    },
    {
        "username": "danny_g1909",
        "full_name": "Danny Dilip George"
    },
    {
        "username": "abhay8017kumar",
        "full_name": "Abhay Kumar"
    },
    {
        "username": "keerthi_erpina",
        "full_name": "Keerthi"
    },
    {
        "username": "its_not_malvika",
        "full_name": "Malavika Nair"
    },
    {
        "username": "dhakshiithh",
        "full_name": "Dhakshith S"
    },
    {
        "username": "gaurav_rampuria_",
        "full_name": "Gaurav Rampuria"
    },
    {
        "username": "areenmahich",
        "full_name": "Areen Mahich"
    },
    {
        "username": "mukun.d_07",
        "full_name": "Mukund Aher"
    },
    {
        "username": "shrutisekharr",
        "full_name": "Shruti Sekhar"
    },
    {
        "username": "srija961d",
        "full_name": "Srija"
    },
    {
        "username": "akshatsinghania_07",
        "full_name": "Akshat Singhania"
    },
    {
        "username": "pranayc_04",
        "full_name": "Pranay Chaudhari"
    },
    {
        "username": "__aayush__singh__0",
        "full_name": "Aayush Singh"
    },
    {
        "username": "xero.shivang",
        "full_name": "Shivang Pandey"
    },
    {
        "username": "sujashagrawal01",
        "full_name": "Sujash Agrawal"
    },
    {
        "username": "harshitaawasthi105",
        "full_name": "Harshita Awasthi"
    },
    {
        "username": "panseyashwardhan",
        "full_name": "Yashwardhan Panse"
    },
    {
        "username": "stellar_society_iitpkd",
        "full_name": "Stellar Society"
    },
    {
        "username": "prashant_sahu_05",
        "full_name": "Prashant kumar"
    },
    {
        "username": "armaan_pasayat_1729",
        "full_name": "Armaan Pasayat"
    },
    {
        "username": "fahadkhanfrs",
        "full_name": "Mohammad Fahad ibn Farhan"
    },
    {
        "username": "tushar_0416",
        "full_name": "Tushar dua"
    },
    {
        "username": "vaibhav_itauriya",
        "full_name": "Vaibhav Itauriya"
    },
    {
        "username": "srivastavatarushi07",
        "full_name": "Tarushi Srivastava"
    },
    {
        "username": "swayam.mane",
        "full_name": "Swayam_mane"
    },
    {
        "username": "im_jeev_n",
        "full_name": "Jeevan Kumar Gadde"
    },
    {
        "username": "aarush_ghate",
        "full_name": "Aarush Ghate"
    },
    {
        "username": "piyush_spectro",
        "full_name": "Piyush"
    },
    {
        "username": "shivangsonker23",
        "full_name": "Shivang"
    },
    {
        "username": "mohit.rawat_03",
        "full_name": "Mohit Rawat"
    },
    {
        "username": "anikag06",
        "full_name": "Anika Gupta"
    },
    {
        "username": "aaaryaaksh",
        "full_name": "Akshyat Arya"
    },
    {
        "username": "aryank5563",
        "full_name": "aryan k"
    },
    {
        "username": "gouravyadavkhosya",
        "full_name": "Gourav Yadav Khosya"
    },
    {
        "username": "sarathkumar9997",
        "full_name": "Sarath Kumar"
    },
    {
        "username": "priyankapaliwal973",
        "full_name": "Priyanka"
    },
    {
        "username": "harshitraj443",
        "full_name": "Harshit Raj"
    },
    {
        "username": "sarthak__2004_08",
        "full_name": "sarthak singh"
    },
    {
        "username": "samarthsahu116",
        "full_name": "samarth sahu"
    },
    {
        "username": "_simplyraihan_",
        "full_name": "Raihan Kakkat"
    },
    {
        "username": "rigved_koli24",
        "full_name": "Rigved Bhalchandra Koli"
    },
    {
        "username": "suryansh__rastogi",
        "full_name": "Suryansh Rastogi"
    },
    {
        "username": "avaneesh_p01",
        "full_name": "Avaneesh P"
    },
    {
        "username": "sanyam_4705",
        "full_name": "Sanyam Jain"
    },
    {
        "username": "scientist.pankaj",
        "full_name": "PANKAJ SHARMA"
    },
    {
        "username": "nitesh_kumar0906",
        "full_name": "Nitesh kumar"
    },
    {
        "username": "peeyushag5",
        "full_name": "Peeyush Agarwal"
    },
    {
        "username": "adwaaiit_2424",
        "full_name": "Adwaaiit Pande"
    },
    {
        "username": "_vaishalikamath",
        "full_name": "Vaishali"
    },
    {
        "username": "harinkhedekunal",
        "full_name": "KUNAL HARINKHEDE"
    },
    {
        "username": "jatiinn_03",
        "full_name": "Jatin"
    },
    {
        "username": "saurav_raj_2003",
        "full_name": "Sãûrãv Râj"
    },
    {
        "username": "___kshitij.the.one___",
        "full_name": "Kshitij Srivastava"
    },
    {
        "username": "itsaarav_yuvraj",
        "full_name": "Sam Sunny"
    },
    {
        "username": "manas_kr_11",
        "full_name": "Manas Kumar"
    },
    {
        "username": "vedantiwari.exe",
        "full_name": "vedant"
    },
    {
        "username": "kanika_865_",
        "full_name": "Kanika_865"
    },
    {
        "username": "anupampriadarshi",
        "full_name": "Anupam Priadarshi"
    },
    {
        "username": "saaumitra.raaj",
        "full_name": "Saaumitra Raaj"
    },
    {
        "username": "aarav12x2",
        "full_name": "Aarav Oswal"
    },
    {
        "username": "shivanandsankpal1313",
        "full_name": "shiVanandSanKpal284"
    },
    {
        "username": "prince.y23",
        "full_name": "Prince Yadav"
    },
    {
        "username": "the__shivam__meena",
        "full_name": "Shivam Meena"
    },
    {
        "username": "rohanraj2814",
        "full_name": "Rohan Raj"
    },
    {
        "username": "akshita._.17",
        "full_name": "akshita"
    },
    {
        "username": "kushagrasingh100",
        "full_name": "Kushagra Singh"
    },
    {
        "username": "a.rush.up",
        "full_name": "Arush Upadhyaya"
    },
    {
        "username": "tanay___20",
        "full_name": "Tanay Pathode"
    },
    {
        "username": "prakhar.kaushal",
        "full_name": "Prakhar Kaushal"
    },
    {
        "username": "akshatshahjade",
        "full_name": "Akshat Shahjade"
    },
    {
        "username": "ayush_srivastava5828",
        "full_name": "Ayush Srivastava"
    },
    {
        "username": "tanush.goel247",
        "full_name": "Tanush Goel"
    },
    {
        "username": "hansikagupta_28",
        "full_name": "Hans🤍"
    },
    {
        "username": "rahulmahala_y23",
        "full_name": "Rahul"
    },
    {
        "username": "khandelia_aditi",
        "full_name": "Aditi Khandelia"
    },
    {
        "username": "rahulg_6924",
        "full_name": "Rahul Ghunawat"
    },
    {
        "username": "ve_harsh_iitk",
        "full_name": "Harsh Verma"
    },
    {
        "username": "smartvivek30",
        "full_name": "Vivek Gautam"
    },
    {
        "username": "_abhi.mn",
        "full_name": "Abhishek Meena🎐♓️"
    },
    {
        "username": "rtanmay588",
        "full_name": "Tanmay Roy"
    },
    {
        "username": "rupant_ted",
        "full_name": "rupant dixit"
    },
    {
        "username": "h.ar_anand",
        "full_name": "Harshit Anand"
    },
    {
        "username": "priyankaa2495",
        "full_name": "Priyanka Arora"
    },
    {
        "username": "kartik.sehra_iitk",
        "full_name": "Kartik Sehra"
    },
    {
        "username": "ashik._.stenny",
        "full_name": "Ashik Stenny"
    },
    {
        "username": "unordinary_substance",
        "full_name": "Aaryan Maheshwari"
    },
    {
        "username": "prem_1304_",
        "full_name": "Prem"
    },
    {
        "username": "mouli_naidu_10",
        "full_name": "bujji😄😄"
    },
    {
        "username": "krishnaagrawal5002",
        "full_name": "Krishna_Agrawal"
    },
    {
        "username": "ankit_at_home",
        "full_name": "Ankit Raj"
    },
    {
        "username": "d3v4n5h_",
        "full_name": "Devansh Chaudhary"
    },
    {
        "username": "krsnaronaldo",
        "full_name": ""
    },
    {
        "username": "rishabh_2625",
        "full_name": "Rishabh Yadav"
    },
    {
        "username": "institnews2.0",
        "full_name": ""
    },
    {
        "username": "abhi25_07",
        "full_name": "Abhisekh"
    },
    {
        "username": "_khushi_.agarwal_",
        "full_name": "KHUSHI AGARWAL"
    },
    {
        "username": "pihurajesh1",
        "full_name": "Yamador"
    },
    {
        "username": "srishtirajora_35_21",
        "full_name": "Srishti Singh Rajora"
    },
    {
        "username": "jjbigdub",
        "full_name": "Pranav Krishna"
    },
    {
        "username": "nipamghorai",
        "full_name": "Nipam Ghorai"
    },
    {
        "username": "aryavart_dahiya_7",
        "full_name": "Aryavart Dahiya"
    },
    {
        "username": "srujan.b_1488",
        "full_name": "Srujan Bhirud"
    },
    {
        "username": "jatin.agrawa1",
        "full_name": "Jatin Agrawal"
    },
    {
        "username": "sudhanshu_saroj",
        "full_name": "SUDHANSHU SAROJ"
    },
    {
        "username": "ayush._._garg",
        "full_name": "Ayush Garg"
    },
    {
        "username": "rohan_kumr_53532211",
        "full_name": "RoHaN  KuMaR ✨"
    },
    {
        "username": "_jon_lannister",
        "full_name": "Deepak Singh"
    },
    {
        "username": "krish2005arora",
        "full_name": "Krish Arora"
    },
    {
        "username": "avm__22",
        "full_name": "Avanee Madnoorkar"
    },
    {
        "username": "outlier_shayar",
        "full_name": "Sunil Pandey"
    },
    {
        "username": "pranjal_dixit25",
        "full_name": "Pranjal Dixit"
    },
    {
        "username": "mahtuog._",
        "full_name": "Goutham"
    },
    {
        "username": "ananyaverma17_",
        "full_name": "Ananya Verma"
    },
    {
        "username": "chhavitanwar_",
        "full_name": "Chhavi Tanwar 💚"
    },
    {
        "username": "_lavina_goyal_",
        "full_name": "Lavina Goyal"
    },
    {
        "username": "soumyajit._.halder",
        "full_name": "Soumyajit Halder"
    },
    {
        "username": "freemindedvibhor",
        "full_name": "Vibhor Anand"
    },
    {
        "username": "_siddiqui_waqar",
        "full_name": "Waqar Siddiqui"
    },
    {
        "username": "shlokmishra08",
        "full_name": "Shlok Mishra"
    },
    {
        "username": "mahak_12_11",
        "full_name": "Mahak Garg"
    },
    {
        "username": "sunn_ykumar8864",
        "full_name": "sunny kumar"
    },
    {
        "username": "rohit.atkurkar",
        "full_name": "Rohit Atkurkar"
    },
    {
        "username": "mainak9093",
        "full_name": "Mainak"
    },
    {
        "username": "satwikrajwadhwa",
        "full_name": "Satwik Raj Wadhwa"
    },
    {
        "username": "diwakarvashi",
        "full_name": "Vashi Diwakar"
    },
    {
        "username": "ridhamds",
        "full_name": "Ridham Solanki"
    },
    {
        "username": "vibha.narayan",
        "full_name": "Vibha Narayan"
    },
    {
        "username": "raunit_49",
        "full_name": "Raunit"
    },
    {
        "username": "nikit_a.67852",
        "full_name": "Nikit@🦋"
    },
    {
        "username": "venugopal.29",
        "full_name": "venu gopal"
    },
    {
        "username": "agarwal.yashwi",
        "full_name": "Yashwi Agarwal"
    },
    {
        "username": "safi_prabhu",
        "full_name": "Prabhu Safi"
    },
    {
        "username": "arsal._.asif",
        "full_name": "محمد ارسل اسف"
    },
    {
        "username": "pratul9999",
        "full_name": "Pratul Koolwal"
    },
    {
        "username": "tejas_q06",
        "full_name": "Tejas singh"
    },
    {
        "username": "rahuliitk27",
        "full_name": "RAHUL MEENA"
    },
    {
        "username": "sachinu629",
        "full_name": "Sachin upadhyay"
    },
    {
        "username": "vivekanandagirihaobijam.17",
        "full_name": "Vivekanandagiri Haobijam"
    },
    {
        "username": "ayus.hksingh",
        "full_name": "Ayush Kumar Singh"
    },
    {
        "username": "adi70615",
        "full_name": "Aditya Anand"
    },
    {
        "username": "parvjain255",
        "full_name": "Parv Jain"
    },
    {
        "username": "harshashok05",
        "full_name": "Harsh"
    },
    {
        "username": "tejrajput_73_r",
        "full_name": "Tej Rajput"
    },
    {
        "username": "its_anuja_artist",
        "full_name": "The Artist 💁‍♀️"
    },
    {
        "username": "aaryaman2016",
        "full_name": "aaryaman"
    },
    {
        "username": "chaitanyagoel29",
        "full_name": "Chaitanya Goel"
    },
    {
        "username": "medhaagarwal__",
        "full_name": "Medha Agarwal"
    },
    {
        "username": "harshverma6817",
        "full_name": "Harsh Verma"
    },
    {
        "username": "tasho4378",
        "full_name": "Tasho Khan"
    },
    {
        "username": "yashwanthholla",
        "full_name": "Yashwanth Yashwanth Holla"
    },
    {
        "username": "ramurathlavath33",
        "full_name": "Ramu Rathod"
    },
    {
        "username": "lakshya_kukreja7",
        "full_name": "Lakshya Kukreja"
    },
    {
        "username": "rksingh954024",
        "full_name": "Rahul Singh"
    },
    {
        "username": "instaexplorer5555",
        "full_name": "InstaExplorer"
    },
    {
        "username": "dev_sah7",
        "full_name": "Mannu Dev Sah"
    },
    {
        "username": "hasir__dh",
        "full_name": "Hasir Dh"
    },
    {
        "username": "himanshu_4932singh",
        "full_name": "Himanshu Singh"
    },
    {
        "username": "_krtyk_",
        "full_name": "Kartik Sharma"
    },
    {
        "username": "_pulakits",
        "full_name": "Pulakit Gajipara"
    },
    {
        "username": "joshimegha25",
        "full_name": "DrMegha Joshi"
    },
    {
        "username": "_cute.fishy",
        "full_name": "Nemo: The Explorer"
    },
    {
        "username": "sai_dishanth",
        "full_name": "Sai Dishanth Banoth"
    },
    {
        "username": "amigochords",
        "full_name": "Vishal Sethi"
    },
    {
        "username": "himanshu_sharma_rers",
        "full_name": "Himanshu Sharma"
    },
    {
        "username": "_.anilgaur",
        "full_name": "Anil Gaur"
    },
    {
        "username": "alwayssiddharthchauhan",
        "full_name": "The Siddharth Chauhan🇮🇳"
    },
    {
        "username": "tanmayyzz",
        "full_name": "Tanmay Mishra"
    },
    {
        "username": "brave_bhavin",
        "full_name": ""
    },
    {
        "username": "ishhhhhhuuuuu",
        "full_name": "Shivam Shaw"
    },
    {
        "username": "_simran0029",
        "full_name": "| सिमरन |"
    },
    {
        "username": "unique_student369",
        "full_name": "Manish Dhangar"
    },
    {
        "username": "ronweasley550",
        "full_name": "Ronav Puri"
    },
    {
        "username": "deepak110212",
        "full_name": "Deepak Goyal"
    },
    {
        "username": "absolute.adarsh",
        "full_name": "A D A R S H 🐼"
    },
    {
        "username": "majormonkistry",
        "full_name": "asturya"
    },
    {
        "username": "blu_malik3",
        "full_name": "Neelaksha Malik"
    },
    {
        "username": "prakriti101105",
        "full_name": "Prakriti Prasad"
    },
    {
        "username": "notadarsing",
        "full_name": "Adarsh Singh"
    },
    {
        "username": "raditya_0079",
        "full_name": "🅰ďîťÿà ®αńjàń ™©"
    },
    {
        "username": "aruz_a.z",
        "full_name": "Aruz Awasthi"
    },
    {
        "username": "_keerthana.d",
        "full_name": "Keerthana"
    },
    {
        "username": "shubh.1225",
        "full_name": "shubh bansal"
    },
    {
        "username": "choudhury.devesh5905_",
        "full_name": "Devesh Choudhury"
    },
    {
        "username": "sapra.vihaan2",
        "full_name": "Vihaan Sapra"
    },
    {
        "username": "ataanuuu",
        "full_name": "Atanu Biswas"
    },
    {
        "username": "shubh_._am_._i",
        "full_name": "•°S H U B H A M°•"
    },
    {
        "username": "manipranshu",
        "full_name": "Pranshu Mani"
    },
    {
        "username": "kshitij._.gupta._",
        "full_name": "Kshitij Gupta"
    },
    {
        "username": "ishaan_1539",
        "full_name": "Ishaan Jain"
    },
    {
        "username": "its._.shrasti",
        "full_name": "Shrasti Dwivedi"
    },
    {
        "username": "ins_arthak18",
        "full_name": "@sarthak_shekhar"
    },
    {
        "username": "anirudh_0317",
        "full_name": "Anirudh"
    },
    {
        "username": "shaurya7_",
        "full_name": "Shaurya Agarwal"
    },
    {
        "username": "shivamlal54",
        "full_name": "Shivam Lal"
    },
    {
        "username": "tensor.1729",
        "full_name": "Kshitij Bhardwaj"
    },
    {
        "username": "sangamgupta8861",
        "full_name": "Sangam Gupta"
    },
    {
        "username": "siddhant_sr03",
        "full_name": "siddhant srivastava"
    },
    {
        "username": "raelinosane",
        "full_name": "Raelino Sane"
    },
    {
        "username": "princy_hirpara",
        "full_name": "PRINCY HIRPARA"
    },
    {
        "username": "engineering_videography",
        "full_name": "B.Tech"
    },
    {
        "username": "qwenkkl",
        "full_name": "جاویددرزاده"
    },
    {
        "username": "devansh.16ojha",
        "full_name": "Devansh Ojha"
    },
    {
        "username": "scientificshrey",
        "full_name": "Shrey Solanki"
    },
    {
        "username": "siri_jonnala__",
        "full_name": "Hema Prasad"
    },
    {
        "username": "njalgo",
        "full_name": "Nitik Jain"
    },
    {
        "username": "haiderfakhar3",
        "full_name": "Block boy"
    },
    {
        "username": "sleepyy_shutter03",
        "full_name": "sakshi"
    },
    {
        "username": "sahil_bhardwaj_608",
        "full_name": "social media digital marketing"
    },
    {
        "username": "purva_patil1105",
        "full_name": "Purva Patil"
    },
    {
        "username": "nevishpathe",
        "full_name": "Nevish Pathe"
    },
    {
        "username": "harshdixit9307",
        "full_name": "Harsh Dixit"
    },
    {
        "username": "viral_chitlangia",
        "full_name": "Viral Chitlangia"
    },
    {
        "username": "shr_utii_16",
        "full_name": "𝚂𝚑𝚛𝚞𝚝𝚒"
    },
    {
        "username": "suryansh7gupta",
        "full_name": ""
    },
    {
        "username": "subhamanand175",
        "full_name": "Subham Anand"
    },
    {
        "username": "jatinmadan1205",
        "full_name": "Jatin Madan"
    },
    {
        "username": "bhaskar_4486",
        "full_name": "Bhaskar Tejavath"
    },
    {
        "username": "dp15320",
        "full_name": ""
    },
    {
        "username": "rd_patel756",
        "full_name": "Rhut Patel"
    },
    {
        "username": "srivabhi2004",
        "full_name": "Abhishek Srivastava"
    },
    {
        "username": "srijann.77",
        "full_name": "Srijan Anand"
    },
    {
        "username": "pragatiagr1",
        "full_name": "Pragati Agrawal"
    },
    {
        "username": "jarwal_pankaj_750",
        "full_name": "🪴Jarwal Pankaj"
    },
    {
        "username": "thepratyush07",
        "full_name": "i_party_u_shhh!!!"
    },
    {
        "username": "akashbhoi.out",
        "full_name": "Akash Kumar Bhoi"
    },
    {
        "username": "complex_but_real",
        "full_name": "Prabhanshu !!"
    },
    {
        "username": "dhruvg_17",
        "full_name": "Dhruv Gupta"
    },
    {
        "username": "divyansh.yellove",
        "full_name": "Divyansh Shah"
    },
    {
        "username": "aatifhasan2206",
        "full_name": "Aatif Hasan"
    },
    {
        "username": "sruthi_sub",
        "full_name": "Sruthi Subramanian"
    },
    {
        "username": "xx___anmol___xx",
        "full_name": "Anmoldeep Singh Dhillon"
    },
    {
        "username": "_kuldeep_thakare",
        "full_name": "Kuldeep Thakare"
    },
    {
        "username": "the_shrutisinha",
        "full_name": "Shruti Sinha"
    },
    {
        "username": "aryaaayyyy",
        "full_name": "Arya Lodha"
    },
    {
        "username": "ansh.ika7634",
        "full_name": ""
    },
    {
        "username": "pratik025raj",
        "full_name": "Pratik Raj"
    },
    {
        "username": "editorshoot",
        "full_name": "CYBER SECURITY."
    },
    {
        "username": "ar.iitk",
        "full_name": "Aerial Robotics IITK"
    },
    {
        "username": "anubhavgupta493",
        "full_name": "Anubhav Gupta"
    },
    {
        "username": "ashwin_chaubey04",
        "full_name": "Ashwin Chaubey"
    },
    {
        "username": "noneoff638",
        "full_name": ""
    },
    {
        "username": "viveknj1",
        "full_name": "Vivek Kumar"
    },
    {
        "username": "anki_kmr21",
        "full_name": "ankit kumar"
    },
    {
        "username": "santosh_k_mathur",
        "full_name": "Santosh Mathur"
    },
    {
        "username": "gupta_dhruv03",
        "full_name": "Dhruv Gupta"
    },
    {
        "username": "kgarg_1",
        "full_name": "Karunaya Garg"
    },
    {
        "username": "akashkumargupta86",
        "full_name": "Akash Kumar Gupta"
    },
    {
        "username": "___sisyphus__",
        "full_name": "aryaman goel"
    },
    {
        "username": "sch_iitk",
        "full_name": "Science Coffee House, IITK"
    },
    {
        "username": "_the_raman_verma_",
        "full_name": "Raman Verma 🐺"
    },
    {
        "username": "prabhat_kumar_iitk",
        "full_name": "Prabhat Kumar"
    },
    {
        "username": "manas220612",
        "full_name": "Manas Ranjan"
    },
    {
        "username": "samarthagarwal622",
        "full_name": "Samarth Agarwal"
    },
    {
        "username": "_hemant_choudhary._",
        "full_name": "Hemant Choudhary"
    },
    {
        "username": "krs_s21",
        "full_name": "Krish Sharma"
    },
    {
        "username": "_._varshhaaaaaa_._",
        "full_name": "Varsha Khandelwal"
    },
    {
        "username": "sumit_s49",
        "full_name": "Sumit"
    },
    {
        "username": "unmeasured_qubit",
        "full_name": "Sumay Avi"
    },
    {
        "username": "mrudul_thakkurwar",
        "full_name": "Mrudul"
    },
    {
        "username": "abisanth2174",
        "full_name": "TM Abisanth"
    },
    {
        "username": "justmohitr",
        "full_name": "Mohit Rajpoot"
    },
    {
        "username": "shiv.wrath_04",
        "full_name": "Shivam Rathore"
    },
    {
        "username": "jiyanshu_dhaka",
        "full_name": "Jiyanshu Dhaka"
    },
    {
        "username": "dil_ke_alfaaz486",
        "full_name": "𝙳𝚒𝚕_𝚔𝚎_𝚊𝚕𝚏𝚊𝚊𝚣 486"
    },
    {
        "username": "akashkk_",
        "full_name": "Akash Kumar🖤"
    },
    {
        "username": "narendra.05__",
        "full_name": "Narendra Ahirwar"
    },
    {
        "username": "anonymity_._rs",
        "full_name": ""
    },
    {
        "username": "sunburnt_horizon",
        "full_name": "Aryan Verma"
    },
    {
        "username": "ssoc.iitk",
        "full_name": "Sleeping Society IIT Kanpur"
    },
    {
        "username": "aadityayadav239",
        "full_name": "Aaditya Yadav"
    },
    {
        "username": "abhimanyu_6604_",
        "full_name": "Abhimanyu Singh"
    },
    {
        "username": "siddharth_220903",
        "full_name": "Siddharth Garg"
    },
    {
        "username": "shubham.mauryya",
        "full_name": "Shubham Maurya"
    },
    {
        "username": "chayan___0",
        "full_name": "Chayan"
    },
    {
        "username": "_vishaka_2_19",
        "full_name": "Vishaka Sharma"
    },
    {
        "username": "mr.alexander.ecose",
        "full_name": "Mr Alexander"
    },
    {
        "username": "sriahila",
        "full_name": "Sri Ahila"
    },
    {
        "username": "rohanik0204",
        "full_name": "Nikhil Rohan"
    },
    {
        "username": "ashutoshk827",
        "full_name": "Ashutosh"
    },
    {
        "username": "imakashbhoi",
        "full_name": "Akash Kumar Bhoi"
    },
    {
        "username": "_akshay_kumar912",
        "full_name": "𝐀𝐤𝐬𝐡𝐚𝐲 𝐤𝐮𝐦𝐚𝐫 (𝐈𝐈𝐓𝐊'𝟐𝟔)"
    },
    {
        "username": "riteshyn",
        "full_name": "Ritesh"
    },
    {
        "username": "kravi9695",
        "full_name": "Ravi Kumar"
    },
    {
        "username": "its_piyush_99",
        "full_name": "P I Y U S H"
    },
    {
        "username": "yashkm_057",
        "full_name": "Yash"
    },
    {
        "username": "sooryansh_malani",
        "full_name": "Sooryansh Malani"
    },
    {
        "username": "rrashii_123",
        "full_name": "Rashi Gupta"
    },
    {
        "username": "light_yerhs",
        "full_name": "Betelgeuse"
    },
    {
        "username": "the_chivaltruistic_ensorceller",
        "full_name": "Utkarsh"
    },
    {
        "username": "aryan50x",
        "full_name": "Aryan Singh"
    },
    {
        "username": "rk15411man",
        "full_name": "Raushan Kumar"
    },
    {
        "username": "hemantjangid219",
        "full_name": "Hemant Jangid"
    },
    {
        "username": "titiksha_1610",
        "full_name": "Titiksha Raval"
    },
    {
        "username": "prathamesh_ladhe",
        "full_name": "𝙿𝚛𝚊𝚝𝚑𝚊𝚖𝚎𝚜𝚑 𝙻𝚊𝚍𝚑𝚎"
    },
    {
        "username": "iitjeevananish",
        "full_name": "Iit jeevan Anish"
    },
    {
        "username": "pranshukindasus",
        "full_name": "Pranshu Thirani"
    },
    {
        "username": "tanxeelaaa",
        "full_name": "تنزیلا 🥀"
    },
    {
        "username": "pushpendrameena5605",
        "full_name": "Pushpendra Meena"
    },
    {
        "username": "vaibhav_304",
        "full_name": "Vaibhav Jha"
    },
    {
        "username": "narrow_intelligence",
        "full_name": "okay enough stalking"
    },
    {
        "username": "nitesh_km22",
        "full_name": "Nitesh Kumar"
    },
    {
        "username": "its_.vishakha10",
        "full_name": "Vishakha Goyal"
    },
    {
        "username": "tenthtak",
        "full_name": "Tenth Tak"
    },
    {
        "username": "samarthpawar645",
        "full_name": "Samarth Pawar"
    },
    {
        "username": "_sofiyaann_",
        "full_name": "Sofiyaan Sameer"
    },
    {
        "username": "oneprathamsahu",
        "full_name": "Pratham Sahu"
    },
    {
        "username": "nisaw_axetin",
        "full_name": "Nitin"
    },
    {
        "username": "hritvija_singh",
        "full_name": "Hritvija Singh"
    },
    {
        "username": "praneeetha1",
        "full_name": "Praneetha Rao"
    },
    {
        "username": "juee_c",
        "full_name": "Juee Chandrachud"
    },
    {
        "username": "kforkeshav_",
        "full_name": "Keshav Kapoor"
    },
    {
        "username": "adit.thakur26",
        "full_name": "Aditya Thakur"
    },
    {
        "username": "sahusk2002",
        "full_name": "Krishna Sahu"
    },
    {
        "username": "adityasuman8",
        "full_name": "Aditya suman"
    },
    {
        "username": "abhik.biswas03",
        "full_name": "Abhik"
    },
    {
        "username": "narottam_kumar_2002",
        "full_name": "Narottam Kumar"
    },
    {
        "username": "rabisankar_dly",
        "full_name": "🦅"
    },
    {
        "username": "_ahemaziz_singh",
        "full_name": "Ahemaziz Singh"
    },
    {
        "username": "behappy5256",
        "full_name": "Behappy"
    },
    {
        "username": "_prabal_01",
        "full_name": "Prabal"
    },
    {
        "username": "amisha.shivran",
        "full_name": ""
    },
    {
        "username": "manasviyadav1945",
        "full_name": "Manasvi Yadav"
    },
    {
        "username": "an.shoooo",
        "full_name": "Anshu Kumar"
    },
    {
        "username": "_dhananjay____",
        "full_name": "Dhananjay Dixit"
    },
    {
        "username": "lakshyta_mahajan_",
        "full_name": "Lakshyta Mahajan"
    },
    {
        "username": "t.kesh201",
        "full_name": "Tanay Kesharwani"
    },
    {
        "username": "vivek_goyal26",
        "full_name": "Vivek Goyal➿"
    },
    {
        "username": "avanti.wasekar",
        "full_name": "Avanti Wasekar"
    },
    {
        "username": "ramjiydv_iitk",
        "full_name": "Ramji Yadav"
    },
    {
        "username": "madddhav",
        "full_name": "Madhav Maheshwari"
    },
    {
        "username": "simranbror",
        "full_name": "Simran Bror🍁"
    },
    {
        "username": "maybe__anshika",
        "full_name": "Anshika Singh"
    },
    {
        "username": "kgkhushgupta",
        "full_name": "khush💫"
    },
    {
        "username": "scienmanas",
        "full_name": "Manas"
    },
    {
        "username": "_e3sh_",
        "full_name": "Eeshwari Sunkersett"
    },
    {
        "username": "rahul_rsa873",
        "full_name": "Rahul Singh Anuragi"
    },
    {
        "username": "anya_11.06",
        "full_name": "Anya Rajan"
    },
    {
        "username": "riteshhans15",
        "full_name": "Riteshhhh🐍"
    },
    {
        "username": "niche9_21",
        "full_name": "niche"
    },
    {
        "username": "arnav_2103",
        "full_name": "Arnav Karipae"
    },
    {
        "username": "pragati1523",
        "full_name": "Pragati Rathi"
    },
    {
        "username": "mudit_sengar",
        "full_name": "Mudit Sengar"
    },
    {
        "username": "yash_1q1",
        "full_name": "Yash Jarwal"
    },
    {
        "username": "krishna._.paswan",
        "full_name": "Krishna Paswan"
    },
    {
        "username": "mr_sidak_kalra",
        "full_name": "Sidak Singh Kalra"
    },
    {
        "username": "vitul.bansal",
        "full_name": "वितुल बंसल🌱"
    },
    {
        "username": "umesh_tayde_2002",
        "full_name": "Umesh Tayde"
    },
    {
        "username": "arryyaaannnn",
        "full_name": "Aru"
    },
    {
        "username": "agam_pipersenia",
        "full_name": "Agam Pipersenia"
    },
    {
        "username": "sparsh19.gupta",
        "full_name": "Sparsh Gupta"
    },
    {
        "username": "khushboo_raii",
        "full_name": "Khushboo Rai"
    },
    {
        "username": "sahil__infinity",
        "full_name": "Sahil Kumar"
    },
    {
        "username": "chhikara_029",
        "full_name": "Harshit Chhikara"
    },
    {
        "username": "encore3.7",
        "full_name": ""
    },
    {
        "username": "kunal__kkt",
        "full_name": "Kunal Thakur"
    },
    {
        "username": "i.hamzamasood",
        "full_name": "Hamza Masood"
    },
    {
        "username": "anshuman_2504",
        "full_name": "Anshuman"
    },
    {
        "username": "rythmkumar232",
        "full_name": "Rythm Kumar"
    },
    {
        "username": "jetha_ram17",
        "full_name": "Jᴇᴛʜᴀ Rᴀᴍ"
    },
    {
        "username": "_ruthvik_16",
        "full_name": "Ruthvik Tunuguntla"
    },
    {
        "username": "__kunal8103",
        "full_name": "KuNaL"
    },
    {
        "username": "animesh_madaan",
        "full_name": "Animesh Madaan"
    },
    {
        "username": "srishtichandra89",
        "full_name": "Srishti Chandra"
    },
    {
        "username": "9835soni",
        "full_name": "soni"
    },
    {
        "username": "gill.singh.a",
        "full_name": "Aman Singh Gill"
    },
    {
        "username": "kshitiz.mittal20",
        "full_name": "Kshitiz Mittal"
    },
    {
        "username": "saini_divya_11",
        "full_name": "Divya Saini"
    },
    {
        "username": "anushk.aaaa",
        "full_name": "anushka🪺"
    },
    {
        "username": "iitkq.c",
        "full_name": "IITK Quick Confessions"
    },
    {
        "username": "rocstar_dinesh23",
        "full_name": "Dinesh"
    },
    {
        "username": "pranav_sai_padamati",
        "full_name": "Pranav sai"
    },
    {
        "username": "rishav_raj.22",
        "full_name": "Rishav Raj"
    },
    {
        "username": "pratyush_baiplawat",
        "full_name": "Kuchchi Pratyush Baiplawat"
    },
    {
        "username": "hardikj_1408",
        "full_name": "Hardik Jindal"
    },
    {
        "username": "alphagammapie",
        "full_name": "EnnKayJay"
    },
    {
        "username": "sunnyraja2004",
        "full_name": "Sunny Raja Prasad"
    },
    {
        "username": "depanshu357",
        "full_name": "Depanshu Sahu"
    },
    {
        "username": "rwasdfghk6784856",
        "full_name": "🎉😊avndksnd"
    },
    {
        "username": "ashok_ks7",
        "full_name": "Ashok Saini"
    },
    {
        "username": "chandu_hk__",
        "full_name": ""
    },
    {
        "username": "anaswarkb_013",
        "full_name": "Anaswar K B"
    },
    {
        "username": "_anant_nayak_",
        "full_name": "Anant Nayak"
    },
    {
        "username": "editorshoot12345",
        "full_name": ""
    },
    {
        "username": "anupg124",
        "full_name": "Anup Kashyap"
    },
    {
        "username": "alphaevenzero",
        "full_name": "Subham Singh"
    },
    {
        "username": "gym_and_deadlift",
        "full_name": "DeadBoy"
    },
    {
        "username": "alankritgupta584",
        "full_name": "Alankrit Gupta"
    },
    {
        "username": "namratagram_",
        "full_name": "Namrata Kamat"
    },
    {
        "username": "areeinmishra",
        "full_name": "Areein Mishra"
    },
    {
        "username": "sharma.rashi_04",
        "full_name": "Rashi Sharma"
    },
    {
        "username": "m__a_fyzi97",
        "full_name": "Faiziology Faiziology"
    },
    {
        "username": "kkrishnansh",
        "full_name": "Krishnansh"
    },
    {
        "username": "hummock_hamek",
        "full_name": "Utkarsh Bhatt"
    },
    {
        "username": "danishvasdev22",
        "full_name": "Danish Vasdev"
    },
    {
        "username": "shiktr1785",
        "full_name": "Shubhankar Tripathi"
    },
    {
        "username": "mistah_shantan",
        "full_name": "Shantan Tyagi"
    },
    {
        "username": "_dhruvmittal_",
        "full_name": "Dhruv Mittal"
    },
    {
        "username": "aditya_.modi",
        "full_name": "Aditya Modi"
    },
    {
        "username": "omsv135",
        "full_name": "Om Shivam Verma"
    },
    {
        "username": "samyak5572",
        "full_name": "Samyak Jain"
    },
    {
        "username": "nebulous_monk",
        "full_name": "Yash Bhinwal"
    },
    {
        "username": "akshat_.shrivastav",
        "full_name": "Akshat Shrivastav"
    },
    {
        "username": "superjainoxycilian",
        "full_name": "N"
    },
    {
        "username": "nandiniv_25",
        "full_name": "Nandini Vaid"
    },
    {
        "username": "ritik___shah",
        "full_name": "Ritik Shah"
    },
    {
        "username": "abhishek_sriv466",
        "full_name": "Abhishek Srivastava"
    },
    {
        "username": "bhavyapaturi",
        "full_name": "Bhavya Paturi"
    },
    {
        "username": "sha._.swat_iit",
        "full_name": "SHASWAT"
    },
    {
        "username": "thoughtfulcat1",
        "full_name": ""
    },
    {
        "username": "vanshika_y01",
        "full_name": "Vanshika Yadav"
    },
    {
        "username": "dev_vasu07",
        "full_name": "Vasu N. Shetty"
    },
    {
        "username": "shiv_hash",
        "full_name": "Shivansh Maheshwari"
    },
    {
        "username": "priyanshu_g29",
        "full_name": "Priyanshu Gupta"
    },
    {
        "username": "rahulmahato_23",
        "full_name": "Rahul Mahato"
    },
    {
        "username": "mohiitt_chauhan",
        "full_name": "Mohit Chauhan"
    },
    {
        "username": "cubs_him",
        "full_name": ""
    },
    {
        "username": "_alok.ranjan",
        "full_name": "Alok Ranjan"
    },
    {
        "username": "_you_can.t_see_me_",
        "full_name": ""
    },
    {
        "username": "saurizz_",
        "full_name": "Saurabh Singh"
    },
    {
        "username": "piyush_.ps",
        "full_name": "Piyush Singh"
    },
    {
        "username": "_shashxnk._.s",
        "full_name": "shashank"
    },
    {
        "username": "rohit_sabal_44_________",
        "full_name": "ROHIT"
    },
    {
        "username": "piyush_beegala",
        "full_name": "Piyush Beegala"
    },
    {
        "username": "jathinreddy_37",
        "full_name": "Pula Jathin Reddy"
    },
    {
        "username": "hiteshpateldhyalal",
        "full_name": "Hitesh Patel Dhyalal"
    },
    {
        "username": "_rahul_a22",
        "full_name": "Rahul"
    },
    {
        "username": "salauddin1023",
        "full_name": "Ayaan Ansari"
    },
    {
        "username": "rajendra.pj",
        "full_name": "Rajendra"
    },
    {
        "username": "lalit_y21iitk",
        "full_name": "Lalit Verma"
    },
    {
        "username": "surajhanchinal",
        "full_name": "Suraj Hanchinal"
    },
    {
        "username": "its_pallabb",
        "full_name": "Pallab Mandal"
    },
    {
        "username": "meghsamita",
        "full_name": "Samita Das"
    },
    {
        "username": "venkaatb",
        "full_name": "Venkaat Balaje"
    },
    {
        "username": "garv.it._",
        "full_name": "Garvit"
    },
    {
        "username": "institnews",
        "full_name": "Nikhil j"
    },
    {
        "username": "pathakhula80",
        "full_name": "Suyash Kumar Pathak"
    },
    {
        "username": "arpitkumar.rai.58",
        "full_name": "Arpit Kumar Rai"
    },
    {
        "username": "ambitlife",
        "full_name": "ambit_life"
    },
    {
        "username": "ta_knee_yahaha_",
        "full_name": "Tania"
    },
    {
        "username": "aditi_30.10",
        "full_name": "Aditi Singh"
    },
    {
        "username": "jhalaks1729",
        "full_name": "Jhalak Sharma"
    },
    {
        "username": "rahul.lunaych",
        "full_name": "Rahul Choudhary"
    },
    {
        "username": "varun_tokas3",
        "full_name": "Varun Tokas"
    },
    {
        "username": "aleatory_freak",
        "full_name": "Nikhil Meena"
    },
    {
        "username": "vivek_y_12",
        "full_name": "Vivek Yadav"
    },
    {
        "username": "mrigank_2",
        "full_name": "Mrigank Kumar"
    },
    {
        "username": "_ktg_18",
        "full_name": "Kartik soni"
    },
    {
        "username": "fly_upanita",
        "full_name": "Upanita Barman"
    },
    {
        "username": "raj_karan_3081",
        "full_name": "Raj Karan"
    },
    {
        "username": "kartikeyasati",
        "full_name": "Kartikeya Sati"
    },
    {
        "username": "amishapatel3887",
        "full_name": "Amisha Patel"
    },
    {
        "username": "riya.silotiya_1216",
        "full_name": "Riya Silotiya"
    },
    {
        "username": "sharib_athar",
        "full_name": "Sharib Athar"
    },
    {
        "username": "shreya.iota",
        "full_name": "Shreya Gupta"
    },
    {
        "username": "divyanshi_s24",
        "full_name": "Divyanshi Sharma"
    },
    {
        "username": "ravikumar_4061",
        "full_name": "Ravi Kumar"
    },
    {
        "username": "sanjaimall",
        "full_name": "Sanjai Mall"
    },
    {
        "username": "ananya.alol",
        "full_name": "Ananya Agrawal"
    },
    {
        "username": "_jaryama",
        "full_name": "Amay Raj"
    },
    {
        "username": "yashvala30",
        "full_name": "Vala Yash"
    },
    {
        "username": "attenuator2004",
        "full_name": "Aniket Nandi"
    },
    {
        "username": "unhingedfrog",
        "full_name": "Muditt Khurana"
    },
    {
        "username": "merchant_burhanuddin53",
        "full_name": "Burhanuddin Merchant"
    },
    {
        "username": "_sswastikkk_",
        "full_name": "Swastik Singhal"
    },
    {
        "username": "utkarshxgupta",
        "full_name": "Utkarsh Gupta"
    },
    {
        "username": "_nivin_vinod_",
        "full_name": "Nivin Vinod"
    },
    {
        "username": "itsabhi_326",
        "full_name": "Abhishek Pardhi"
    },
    {
        "username": "anshulnarwariya9",
        "full_name": "Anshul Narwariya"
    },
    {
        "username": "iamrajatsahu",
        "full_name": "Rajat Sahu"
    },
    {
        "username": "gvarsha3",
        "full_name": "Varsha G"
    },
    {
        "username": "_atishhay",
        "full_name": "Atishay Jain"
    },
    {
        "username": "_.sonal.agrawal._",
        "full_name": "Sonal Agrawal"
    },
    {
        "username": "_ak_ar__",
        "full_name": "Akshat"
    },
    {
        "username": "s.ritwikk",
        "full_name": "Ritwik Shankar"
    },
    {
        "username": "sharvil_athaley",
        "full_name": "Sharvil Athaley"
    },
    {
        "username": "anupamanand01",
        "full_name": "Anupam Anand"
    },
    {
        "username": "jaagrati_jain",
        "full_name": "Jaagrati Jain"
    },
    {
        "username": "adxmyt",
        "full_name": "Advait Vashi"
    },
    {
        "username": "prrbhdeep",
        "full_name": "Prabh Deep 🎴"
    },
    {
        "username": "imsandipandutta03",
        "full_name": "Sandipan Dutta"
    },
    {
        "username": "_.aryn.___",
        "full_name": "Aryan"
    },
    {
        "username": "_dhruv_poonia",
        "full_name": "Dhruv"
    },
    {
        "username": "rishabhag_",
        "full_name": "Rishabh Agrawal"
    },
    {
        "username": "the_tempnode",
        "full_name": "Devansh Agarwal"
    },
    {
        "username": "shreenag_c",
        "full_name": "tejas chikoti"
    },
    {
        "username": "hardik_agrwl_1412",
        "full_name": "Hardik Agrawal"
    },
    {
        "username": "_anjali_pandey_45",
        "full_name": "∆njali Pandey"
    },
    {
        "username": "lazy_mitochondria_",
        "full_name": "Anwesh Saha"
    },
    {
        "username": "rounakshr10",
        "full_name": "Rounak Sharma"
    },
    {
        "username": "kartikkulkarni27",
        "full_name": "Kartik Kulkarni"
    },
    {
        "username": "manasvixxjain_",
        "full_name": "MANASVI"
    },
    {
        "username": "_mohikaaa",
        "full_name": "Mohika Agarwal"
    },
    {
        "username": "_siddharth.y_",
        "full_name": "Siddharth Yadav"
    },
    {
        "username": "neil.shirude",
        "full_name": "Neil Shirude"
    },
    {
        "username": "uditpd3000",
        "full_name": "Udit Prasad"
    },
    {
        "username": "d_only_riishav",
        "full_name": "Rishav Bikarwar"
    },
    {
        "username": "_vaishnavisachan_",
        "full_name": "Vaishnavi Sachan"
    },
    {
        "username": "rishi_agrawal_1704",
        "full_name": "Rishi Agrawal"
    },
    {
        "username": "mandar_wayal7",
        "full_name": "Mandar Wayal"
    },
    {
        "username": "porav_rohilla_138__",
        "full_name": "Porav Rohilla"
    },
    {
        "username": "ucshivangi",
        "full_name": "Shivangi Yadav"
    },
    {
        "username": "_recurring_",
        "full_name": "Suket Raj"
    },
    {
        "username": "astrophton",
        "full_name": "Akshat dubey"
    },
    {
        "username": "april_samad",
        "full_name": "April Samad"
    },
    {
        "username": "_praneat_data_",
        "full_name": "Praneat Data"
    },
    {
        "username": "_ghooster_",
        "full_name": "Kumar Arpit"
    },
    {
        "username": "_jayeshbaretiya_",
        "full_name": "Jayesh Baretiya"
    },
    {
        "username": "ravija.chandel",
        "full_name": "Ravija Chandel"
    },
    {
        "username": "_.ayush_himmatsinghka._",
        "full_name": "Ayush"
    },
    {
        "username": "astha.tibs",
        "full_name": "Astha Tibrewal"
    },
    {
        "username": "sarthakkalankar2811",
        "full_name": "Sarthak Kalankar"
    },
    {
        "username": "unrealadi",
        "full_name": "Aditya Bangar"
    },
    {
        "username": "_abhijeet.verma",
        "full_name": "Abhijeet Verma"
    },
    {
        "username": "_nishantp_0605",
        "full_name": "Nishant Patel"
    },
    {
        "username": "kps.nmn",
        "full_name": "Kunwar"
    },
    {
        "username": "mehar_goenka",
        "full_name": "Mehar Goenka"
    },
    {
        "username": "bosonic_string",
        "full_name": "Yash Chaudhary"
    },
    {
        "username": "iyashgoel",
        "full_name": "Yash Goel"
    },
    {
        "username": "mohiit_jangid",
        "full_name": "Mohit jangid"
    },
    {
        "username": "souptik.majumder",
        "full_name": "Souptik Majumder"
    },
    {
        "username": "adithyapandeykumar",
        "full_name": ""
    },
    {
        "username": "the__toxic_one",
        "full_name": "अविरल✨️"
    },
    {
        "username": "mdadil0_0",
        "full_name": "Mohd Adil"
    },
    {
        "username": "arush.kumar.singh",
        "full_name": "Arush Kumar Singh"
    },
    {
        "username": "mo_in_mo_out",
        "full_name": "Moin Ahmed"
    },
    {
        "username": "paras_sharma_18_",
        "full_name": "Paras Sharma"
    },
    {
        "username": "a_khand0421",
        "full_name": "Ankit Khandelwal"
    },
    {
        "username": "pulakgupta_",
        "full_name": "Pulak Gupta"
    },
    {
        "username": "_krishna_1886",
        "full_name": "Krishna Prajapati"
    },
    {
        "username": "salonigrace7",
        "full_name": "Saloni.G"
    },
    {
        "username": "chinmayanand078",
        "full_name": "Chinmay Anand"
    },
    {
        "username": "nikumar6619",
        "full_name": "Nitish"
    },
    {
        "username": "ashutosh_rabia_5911",
        "full_name": "Ashutosh Rabia"
    },
    {
        "username": "ram.dev_121",
        "full_name": "Ramdev."
    },
    {
        "username": "neha_p.1.7.2.9",
        "full_name": "Panuganti Neha"
    },
    {
        "username": "ritul_boora",
        "full_name": "Ritul"
    },
    {
        "username": "dhamijasanya",
        "full_name": "Sanya Dhamija"
    },
    {
        "username": "priyanshu_r_k",
        "full_name": "Priyanshu Kamde"
    },
    {
        "username": "riddhhamm",
        "full_name": "Ridham Modi"
    },
    {
        "username": "kumarrajeev_13",
        "full_name": "Rajeev Kumar"
    },
    {
        "username": "sanyam_.s",
        "full_name": "Sanyam Shivhare"
    },
    {
        "username": "the_ri_s_h_u",
        "full_name": "Riyanshu"
    },
    {
        "username": "mishra_pragyansh",
        "full_name": "Pragyansh Mishra"
    },
    {
        "username": "lakshansh_gujrathi",
        "full_name": "Lakshansh Chouhan"
    },
    {
        "username": "varshney.official",
        "full_name": "𝗨𝗝𝗝𝗪𝗔𝗟 𝗩𝗔𝗥𝗦𝗛𝗡𝗘𝗬"
    },
    {
        "username": "pra.thamesh026",
        "full_name": "Prathamesh"
    },
    {
        "username": "ash_p_18",
        "full_name": "Ashish Patidar"
    },
    {
        "username": "singh_dhruvs",
        "full_name": "ᴹᴿ Ꭰʜʀᴜᴠ ×͜× ᶠᶠ"
    },
    {
        "username": "its_vish_raj",
        "full_name": "Vishap Raj"
    },
    {
        "username": "nayan.nagmani2004",
        "full_name": "NAGMANI NAYAN"
    },
    {
        "username": "jayanth_ragav",
        "full_name": "Jayanth Ragav"
    },
    {
        "username": "dhruv0x0x0",
        "full_name": "Dhruv"
    },
    {
        "username": "__krish__333__",
        "full_name": "krish"
    },
    {
        "username": "jain_aryan_19",
        "full_name": "Aryan Jain"
    },
    {
        "username": "kaneezftma",
        "full_name": "کنیز فاطمہ"
    },
    {
        "username": "ojas_brid_2004",
        "full_name": "Brid Ojas"
    },
    {
        "username": "arihant_roy_10",
        "full_name": "Arihant Roy"
    },
    {
        "username": "desconiitk",
        "full_name": "DesCon Society, IIT Kanpur"
    },
    {
        "username": "junaidahmed2520",
        "full_name": "Junaid Ahmed"
    },
    {
        "username": "sanchit.3301",
        "full_name": "Sanchit Sharma"
    },
    {
        "username": "aanand_me",
        "full_name": "Ashutosh Anand Mehta"
    },
    {
        "username": "akshat_srivastava04",
        "full_name": "Akshat Srivastava"
    },
    {
        "username": "v_nikkhil",
        "full_name": "Nikhil"
    },
    {
        "username": "var_dhruv26",
        "full_name": "Dhruv Varshney"
    },
    {
        "username": "abbaskahan7868",
        "full_name": "Abbas Khan"
    },
    {
        "username": "_shrey2091",
        "full_name": "Shrey Bansal"
    },
    {
        "username": "sankalp.mittal.940",
        "full_name": "Sankalp Mittal"
    },
    {
        "username": "nischay_mittal19",
        "full_name": "Nischay Mittal"
    },
    {
        "username": "gupta_nitansh5354",
        "full_name": "Nitansh Gupta"
    },
    {
        "username": "anas_ali_1018",
        "full_name": "Anas Ali"
    },
    {
        "username": "akash_paijwar",
        "full_name": "Akash Paijwar"
    },
    {
        "username": "nath_yasaswi",
        "full_name": "Yasaswi Nath"
    },
    {
        "username": "kollamoram_karthik",
        "full_name": "k.karthik reddy"
    },
    {
        "username": "_sarthak_657",
        "full_name": "𝗦𝗮𝗿𝘁𝗵𝗮𝗸 𝗣𝗮𝘀𝘄𝗮𝗻"
    },
    {
        "username": "_pankaj76",
        "full_name": "Pankaj Kumar"
    },
    {
        "username": "sheeshram_choudharyy",
        "full_name": "Sheeshram Choudhary"
    },
    {
        "username": "masked_vighnesh",
        "full_name": "Vighnesh Patidar"
    },
    {
        "username": "dashdebarpita",
        "full_name": "Debarpita Dash"
    },
    {
        "username": "verizon_verified_iphone_g_away",
        "full_name": "VERIZON-IPHONE-GIVEAWAY"
    },
    {
        "username": "astitva5530",
        "full_name": "Astitva"
    },
    {
        "username": "q12_3_.0",
        "full_name": "assfthgj"
    },
    {
        "username": "keyansh.vaish",
        "full_name": "Keyansh Vaish"
    },
    {
        "username": "prachi_s101",
        "full_name": "Prachi Choudhary"
    },
    {
        "username": "kushal_072",
        "full_name": "Kushal Bansal"
    },
    {
        "username": "the_7g_girl",
        "full_name": "Sharvani Jadhav"
    },
    {
        "username": "hridhan.patel_oshoo",
        "full_name": "Hridhan Patel"
    },
    {
        "username": "roshan_sanap_22",
        "full_name": "Roshan Sanap"
    },
    {
        "username": "budaniajayant",
        "full_name": "Jayant Budania"
    },
    {
        "username": "its_vinayak_gt",
        "full_name": "Vinayak Gupta"
    },
    {
        "username": "midhun_manojrt",
        "full_name": "Midhun Manoj"
    },
    {
        "username": "im.ahmad.raza",
        "full_name": "Ahmad Raza"
    },
    {
        "username": "satyam_2.71",
        "full_name": "Satyam Kumar"
    },
    {
        "username": "suyashpant",
        "full_name": "Suyash Pant"
    },
    {
        "username": "_adityaraj1",
        "full_name": "Aditya Raj"
    },
    {
        "username": "_ujjwalchoudhary_",
        "full_name": "UC"
    },
    {
        "username": "rohan_nimesh_1",
        "full_name": "Rohan Nimesh"
    },
    {
        "username": "8499lakshmi",
        "full_name": "lakshmi"
    },
    {
        "username": "zoliansangii",
        "full_name": "zo"
    },
    {
        "username": "iitz_satvik",
        "full_name": "Satvik Pratap Singh"
    },
    {
        "username": "raj_patel91252",
        "full_name": "Raj Patel"
    },
    {
        "username": "ananydc4522",
        "full_name": "Anany Dev Choudhary"
    },
    {
        "username": "gaurav__kumar.1923",
        "full_name": "Gaurav Kumar"
    },
    {
        "username": "princekss22",
        "full_name": "Singh Princekumar"
    },
    {
        "username": "mantavya_28",
        "full_name": "Mantavya Upadhyay"
    },
    {
        "username": "anilkushwah07",
        "full_name": "Anil Kushwah"
    },
    {
        "username": "transcendence_01",
        "full_name": "Will Caster"
    },
    {
        "username": "vedant_gitte_02",
        "full_name": "Vedant Gitte"
    },
    {
        "username": "snekund04",
        "full_name": "Sneha Kundu"
    },
    {
        "username": "karthik._bunny_",
        "full_name": "Karthik"
    },
    {
        "username": "pranmitra05",
        "full_name": "Prangopal Mitra"
    },
    {
        "username": "himanshukv6",
        "full_name": "HimanshuKV"
    },
    {
        "username": "nitish.kumar05",
        "full_name": "Nitish Kumar"
    },
    {
        "username": "ak.ankitt",
        "full_name": "Ankit Kaushik"
    },
    {
        "username": "shr_sngh",
        "full_name": "Shaurya Singh"
    },
    {
        "username": "iamsaintist",
        "full_name": "Singana Sri Krishna Sai"
    },
    {
        "username": "choudhary_shray",
        "full_name": "Shray Choudhary"
    },
    {
        "username": "pankajnath475",
        "full_name": "pankaj nath"
    },
    {
        "username": "ritikraj1306",
        "full_name": "Ritik Raj"
    },
    {
        "username": "akshat.kumargupta.54",
        "full_name": "Akshat KG"
    },
    {
        "username": "nischaypatel4",
        "full_name": "Nischay Patel"
    },
    {
        "username": "prerna.singh.chauhan",
        "full_name": "Prerna Singh Chauhan"
    },
    {
        "username": "itsakshay___3337",
        "full_name": "Akshay Choudhary"
    },
    {
        "username": "devesh_mna_85",
        "full_name": "deveshmeena"
    },
    {
        "username": "professional.inc",
        "full_name": "Professional Inc."
    },
    {
        "username": "omkar_prusty",
        "full_name": "OMKAR"
    },
    {
        "username": "_ahmadsayyed",
        "full_name": "Sayed Salim Ahmad (سید سلیم احمد)"
    },
    {
        "username": "abhirajakhouri",
        "full_name": "Abhiraj Akhouri"
    },
    {
        "username": "nigamsirsasth",
        "full_name": "Sirsasthn22"
    },
    {
        "username": "arshitnarang123",
        "full_name": "Arshit"
    },
    {
        "username": "divitshahh_15",
        "full_name": "Divit Shah"
    },
    {
        "username": "shivakshi_57_",
        "full_name": "Shivakshi Lal"
    },
    {
        "username": "jainrachitrj101",
        "full_name": "Rachit Jain"
    },
    {
        "username": "siddhivora04",
        "full_name": "Siddhi Vora"
    },
    {
        "username": "lucksay_08",
        "full_name": "Lakshay Gupta"
    },
    {
        "username": "imanojkr",
        "full_name": "Manoj Kumar"
    },
    {
        "username": "ishan_singh._",
        "full_name": "Ishan Singh"
    },
    {
        "username": "swa_yam_sidh",
        "full_name": "Swayamsidh Pradhan"
    },
    {
        "username": "prakharishan",
        "full_name": "Ishan Prakhar"
    },
    {
        "username": "amritraj1705",
        "full_name": "Amrit Raj"
    },
    {
        "username": "ayushbaghel_01",
        "full_name": "Ayush Baghel"
    },
    {
        "username": "moni_dutt",
        "full_name": "Moni Dutt✨"
    },
    {
        "username": "void_sarthak",
        "full_name": "Sarthak Agarwal"
    },
    {
        "username": "itsach07",
        "full_name": "Anuj Chaudhary"
    },
    {
        "username": "agarwal_prerak7108",
        "full_name": "Prerak Agarwal"
    },
    {
        "username": "raj58._",
        "full_name": "Raj Patel"
    },
    {
        "username": "r.o.h.a.n_b.a.t.r.a",
        "full_name": "Rohan Batra"
    },
    {
        "username": "astro_paaritosh12",
        "full_name": "Paaritosh Jain"
    },
    {
        "username": "divyansh_singh1910",
        "full_name": "Divyansh"
    },
    {
        "username": "deham_15",
        "full_name": "Deham Rajvanshi"
    },
    {
        "username": "aadivanara",
        "full_name": "Aaditya Vanara"
    },
    {
        "username": "purn_ay",
        "full_name": "Purnay Kanchi"
    },
    {
        "username": "sar.vesh_2477",
        "full_name": "Sarvesh Singh"
    },
    {
        "username": "indrajeet2204",
        "full_name": "Indrajeet Pal"
    },
    {
        "username": "shauryas23",
        "full_name": "Shaurya"
    },
    {
        "username": "_divyansh._.garg",
        "full_name": "Divyansh Garg"
    },
    {
        "username": "adithya.lingala",
        "full_name": "Adithya"
    },
    {
        "username": "vanshikag14",
        "full_name": "Vanshikag14"
    },
    {
        "username": "sensai_sid",
        "full_name": "Sidharth Budania"
    },
    {
        "username": "n1tin._.gautam",
        "full_name": "Nitin Gautam"
    },
    {
        "username": "anmolagravanshi",
        "full_name": "Anmol Agrahari"
    },
    {
        "username": "rhydburgerr",
        "full_name": "Ridin Datta"
    },
    {
        "username": "swarnarajd494",
        "full_name": "swarna raj"
    },
    {
        "username": "_ishanx_81",
        "full_name": "Ishan"
    },
    {
        "username": "devkatearvind_18",
        "full_name": "Arvind Devkate"
    },
    {
        "username": "aditi.choudhary.21",
        "full_name": "Aditi"
    },
    {
        "username": "shivpal6282",
        "full_name": "Shiv pal meena"
    },
    {
        "username": "harshiit.k",
        "full_name": "Harshit Kumar"
    },
    {
        "username": "adi_tyaprakash04",
        "full_name": "ADITYA PRAKASH"
    },
    {
        "username": "bhalla_sidharth",
        "full_name": "Sidharth Bhalla"
    },
    {
        "username": "shubh_jx",
        "full_name": "Shubh"
    },
    {
        "username": "kevinthomasbenoy",
        "full_name": "Kevin Thomas Benoy"
    },
    {
        "username": "_harii_04",
        "full_name": "HARIOM SINGH"
    },
    {
        "username": "ajay_456_26",
        "full_name": "अजय सिंह"
    },
    {
        "username": "naitikharbhajanka",
        "full_name": "Naitik Harbhajanka"
    },
    {
        "username": "naksh_1891",
        "full_name": "Nakshatra Anil U"
    },
    {
        "username": "_ankitt.23",
        "full_name": "Ankit"
    },
    {
        "username": "sohamsen0605",
        "full_name": "Soham Sen"
    },
    {
        "username": "singhal_abhi_53",
        "full_name": "Abhinav Singhal"
    },
    {
        "username": "diyasaraf4",
        "full_name": "Diya Saraf"
    },
    {
        "username": "prathamshhhh",
        "full_name": "Pratham shah"
    },
    {
        "username": "manas.016",
        "full_name": "Manas Dhakad"
    },
    {
        "username": "_thenerdyaccount_",
        "full_name": ""
    },
    {
        "username": "prashantverma1944",
        "full_name": "Prashant Verma"
    },
    {
        "username": "manvi_verma_49",
        "full_name": "Manvi Verma"
    },
    {
        "username": "_arnav._.gupta",
        "full_name": "Arnav Gupta"
    },
    {
        "username": "aniket._.kc",
        "full_name": "Aniket Kumar Choudhary"
    },
    {
        "username": "kushagra.1794",
        "full_name": "Kushagra Srivastava"
    },
    {
        "username": "dheerajdagar.dj",
        "full_name": "Dheeraj Dagar"
    },
    {
        "username": "darshini_priya.16",
        "full_name": "Priyadarshini Kumari"
    },
    {
        "username": "diptiyadav517",
        "full_name": "Dipti yadav"
    },
    {
        "username": "taneshqzendey",
        "full_name": "Taneshq Zendey"
    },
    {
        "username": "aadvik.kr",
        "full_name": "𝒜𝒶𝒹𝓋𝒾𝓀 𝒦𝓊𝓂𝒶𝓇"
    },
    {
        "username": "aditya.gtm16",
        "full_name": "Aditya Gautam"
    },
    {
        "username": "devank_snpi",
        "full_name": "Devank Saran Prajapati"
    },
    {
        "username": "divyam.ag",
        "full_name": "DivyamAgarwal"
    },
    {
        "username": "vikranth_v2005",
        "full_name": "Vikranth Vavilapalli"
    },
    {
        "username": "soumyagupta6940",
        "full_name": "soumya gupta"
    },
    {
        "username": "suryansh_49",
        "full_name": "Suryansh Dwivedi"
    },
    {
        "username": "khushig_37",
        "full_name": "Khushi Gupta"
    },
    {
        "username": "bharatkj22",
        "full_name": "Bharat Kumar Jangid"
    },
    {
        "username": "ayush_agarwal_4081",
        "full_name": "Ayush Agarwal"
    },
    {
        "username": "pranjulshikhar",
        "full_name": "Pranjul Shikhar Verma"
    },
    {
        "username": "arpityadav221b",
        "full_name": "Arpit Yadav"
    },
    {
        "username": "shreyas.vaidya.984",
        "full_name": "Shreyas Vaidya"
    },
    {
        "username": "tanyasingh_16",
        "full_name": "Tanya Singh"
    },
    {
        "username": "mars_1729",
        "full_name": ""
    },
    {
        "username": "riyaiitk",
        "full_name": "Riya Mittal"
    },
    {
        "username": "faheem_____nizar",
        "full_name": "Faheem Nizar"
    },
    {
        "username": "ashutosh711.ag",
        "full_name": "Ashutosh Goel"
    },
    {
        "username": "saloni.m25",
        "full_name": "Saloni Mittal"
    },
    {
        "username": "shrewd.tea",
        "full_name": "Shruti Rastogi"
    },
    {
        "username": "ayush__sahu_0402",
        "full_name": "Ayush Sahu"
    },
    {
        "username": "h.ersheys",
        "full_name": "Harshita Chhuttani"
    },
    {
        "username": "vaneesha_0410",
        "full_name": "Vaneesha S Kumar"
    },
    {
        "username": "harshit_iitk",
        "full_name": "Harshit Gupta"
    },
    {
        "username": "manasvi_nid",
        "full_name": "Manasvi N"
    },
    {
        "username": "apoorvtandon2004",
        "full_name": "Apoorv Tandon"
    },
    {
        "username": "khushibayla_31",
        "full_name": "khushi bayla"
    },
    {
        "username": "tanyadevchauhan40p",
        "full_name": "Tanu"
    },
    {
        "username": "prajeetsr15",
        "full_name": "Prajeet Singh Rawat"
    },
    {
        "username": "mehtamahak19",
        "full_name": "Mahak Mehta"
    },
    {
        "username": "mansi_patel.0721",
        "full_name": "Mansi Patel"
    },
    {
        "username": "shashwat_gupta2001",
        "full_name": "Shashwat Gupta"
    },
    {
        "username": "kaniiishkgoyal",
        "full_name": "Kanishk Goyal"
    },
    {
        "username": "shivam.kumar_003",
        "full_name": "Shivam Kumar"
    },
    {
        "username": "parthvijay09",
        "full_name": "Parth Vijay"
    },
    {
        "username": "samprit.sv",
        "full_name": "Samprit S Vadhulas"
    },
    {
        "username": "naizasinglaa",
        "full_name": "Naiza"
    },
    {
        "username": "manya_gupta._.17",
        "full_name": "Manya Gupta"
    },
    {
        "username": "rajarshid_",
        "full_name": "Rajarshi Dutta"
    },
    {
        "username": "electronicsclub.iitk",
        "full_name": "Electronics Club IIT Kanpur"
    },
    {
        "username": "_.sassyboii._",
        "full_name": "Shashank Sinha"
    },
    {
        "username": "firysatta",
        "full_name": "Snehasis Satapathy"
    },
    {
        "username": "shivam1182913",
        "full_name": "Shivam Sharma"
    },
    {
        "username": "sagar.jaiki_",
        "full_name": "jaikisagar"
    },
    {
        "username": "dhruv.budhedeo",
        "full_name": "Dhruv Budhedeo"
    },
    {
        "username": "pravin.tanpure27",
        "full_name": "Pravin Tanpure"
    },
    {
        "username": "aditya_subramanian_",
        "full_name": "Aditya Subramanian"
    },
    {
        "username": "yuval_bansal",
        "full_name": "Yuval Bansal"
    },
    {
        "username": "v_khiladi_",
        "full_name": "Vishal Kumar"
    },
    {
        "username": "nilay_agarwal_",
        "full_name": "Nilay Agarwal"
    },
    {
        "username": "_diprajapati",
        "full_name": "Diwakar Prajapati"
    },
    {
        "username": "tamoghna_k_99",
        "full_name": "Tamoghna"
    },
    {
        "username": "dilkhush_m_",
        "full_name": "Dilkhush Meena"
    },
    {
        "username": "kumaryan.ak",
        "full_name": "ARYAN KUMAR"
    },
    {
        "username": "ptpvt17",
        "full_name": "PT"
    },
    {
        "username": "vm349177",
        "full_name": "Varun Mahajan"
    },
    {
        "username": "rishikeshsahil",
        "full_name": "Rishikesh Sahil"
    },
    {
        "username": "naturelifesun",
        "full_name": "Mayur Agrwal"
    },
    {
        "username": "piyushhhh721",
        "full_name": ""
    },
    {
        "username": "__anshjain_",
        "full_name": "Ansh Jain 🥷"
    },
    {
        "username": "_m.raghav",
        "full_name": "Raghav Manglik"
    },
    {
        "username": "anshu20127",
        "full_name": "anshu yadav"
    },
    {
        "username": "aryan_maurya383",
        "full_name": "Aryan Maurya"
    },
    {
        "username": "230bhavya",
        "full_name": "Bhavya Sharma"
    },
    {
        "username": "saagarkopparam",
        "full_name": "Saagar Kopparam"
    },
    {
        "username": "ayvid.19",
        "full_name": "Divya Choudhary"
    },
    {
        "username": "anitejjain",
        "full_name": "Anitej jain"
    },
    {
        "username": "ujjwal_k_9036",
        "full_name": "Ujjwal Kumar"
    },
    {
        "username": "abhi_abhivardhan",
        "full_name": "Abhi Abhivardhan"
    },
    {
        "username": "sahilpanjwani12",
        "full_name": "Sahil Panjwani"
    },
    {
        "username": "sethu._.spam",
        "full_name": "sethu prasad"
    },
    {
        "username": "sethuprasad.senthil",
        "full_name": "Sethuprasad Senthil"
    },
    {
        "username": "gautamishahil",
        "full_name": "Gautam Baranwal Ttm"
    },
    {
        "username": "jatinalwariya",
        "full_name": "Jatin Alwariya"
    },
    {
        "username": "rishitha04",
        "full_name": "Rishitha"
    },
    {
        "username": "aarsh_kaushik3",
        "full_name": "Aarsh Kaushik"
    },
    {
        "username": "n.a.r.e.n.d.r.a_m.e.e.n.a",
        "full_name": "Narendra Meena"
    },
    {
        "username": "adityaprakash8824",
        "full_name": "Aditya Prakash"
    },
    {
        "username": "rishav_sisodiya24",
        "full_name": "Rishav Raj"
    },
    {
        "username": "aaryan_jain.13",
        "full_name": "Aaryan Jain"
    },
    {
        "username": "gb_optimusprime",
        "full_name": "Gaurang"
    },
    {
        "username": "_adwaitkadam_",
        "full_name": "Adwait Kadam"
    },
    {
        "username": "yashm_1704",
        "full_name": "Yash Meshram"
    },
    {
        "username": "sakinamaner22",
        "full_name": "Sakina Maner"
    },
    {
        "username": "sanketdaphal07",
        "full_name": "Sanket Daphal"
    },
    {
        "username": "piyush_ch754",
        "full_name": "Piyush Chandra"
    },
    {
        "username": "lil_devil_.007",
        "full_name": ""
    },
    {
        "username": "coherent_pranjal",
        "full_name": "Pranjal Singh"
    },
    {
        "username": "saikrishna.swaminathan",
        "full_name": "Saikrishna Swaminathan"
    },
    {
        "username": "jadit_19",
        "full_name": "Adit Jain"
    },
    {
        "username": "himanshugupta2411",
        "full_name": "Himanshu Gupta"
    },
    {
        "username": "shourya.khare",
        "full_name": "Shourya Khare"
    },
    {
        "username": "goyalkinchitiitk",
        "full_name": "Kinchit Goyal"
    },
    {
        "username": "ky.io.oi",
        "full_name": "Ashish Ashish"
    },
    {
        "username": "rushi_d_1911",
        "full_name": "Rushikesh Chary"
    },
    {
        "username": "oomphiest_whoomp",
        "full_name": "Amritansh Tripathi"
    },
    {
        "username": "alt.kshitij_",
        "full_name": ""
    },
    {
        "username": "akanksha_._24",
        "full_name": "Akanksha Wattamwar"
    },
    {
        "username": "yash_soan",
        "full_name": "Yash Soan"
    },
    {
        "username": "devarajkolasure",
        "full_name": "Devaraj Kolasure"
    },
    {
        "username": "prathamesh_baviskar22",
        "full_name": "Prathamesh Baviskar"
    },
    {
        "username": "chintan.dixit.33",
        "full_name": "Chintan Dixit"
    },
    {
        "username": "sourav_sharma_180",
        "full_name": "Sourav Sharma"
    },
    {
        "username": "miteshwandhare",
        "full_name": "Mitesh Wandhare"
    },
    {
        "username": "dharmendrajangir2004",
        "full_name": "Dharmendra Jangir"
    },
    {
        "username": "ab.hilasha949",
        "full_name": "Abhilasha"
    },
    {
        "username": "amipriyaanand",
        "full_name": "Amipriya Anand"
    },
    {
        "username": "7shivam.mishra",
        "full_name": "Shivam Mishra"
    },
    {
        "username": "harshit_784",
        "full_name": "Harshit Srivastava"
    },
    {
        "username": "vishalkumar342003",
        "full_name": "Vishal Kumar"
    },
    {
        "username": "shreyansh.2004_",
        "full_name": "Shreyansh Singh"
    },
    {
        "username": "adarshpal021",
        "full_name": "Adarsh Pal"
    },
    {
        "username": "rudransh.goel",
        "full_name": "Rudransh Goel"
    },
    {
        "username": "harshit.sharma1105",
        "full_name": "Harshit Sharma"
    },
    {
        "username": "trijal_xo",
        "full_name": "Trijal Srivastava"
    },
    {
        "username": "live_iitk",
        "full_name": "Rajvardhan Singhee"
    },
    {
        "username": "adity_gupt_et",
        "full_name": "Aditya Gupta"
    },
    {
        "username": "m.tanishsingla",
        "full_name": "Tanish Singla"
    },
    {
        "username": "naveen_y03",
        "full_name": "Naveen Yadav"
    },
    {
        "username": "_theadityaraj",
        "full_name": "Aditya Raj"
    },
    {
        "username": "winter46._",
        "full_name": "."
    },
    {
        "username": "shreyasmirkale",
        "full_name": "Shreyas Mirkale"
    },
    {
        "username": "_riya_gupta__03",
        "full_name": "Riya Gupta"
    },
    {
        "username": "priyanshij2525",
        "full_name": "Priyanshi Jain"
    },
    {
        "username": "_sha_ra.h",
        "full_name": "sharah"
    },
    {
        "username": "s0umith",
        "full_name": "Soumith Chowdary"
    },
    {
        "username": "monika__marya__",
        "full_name": "Monika Kumari"
    },
    {
        "username": "kishan_euphoric",
        "full_name": "kishan kumar"
    },
    {
        "username": "ish_eunoia",
        "full_name": "Srishti"
    },
    {
        "username": "d_j_yo",
        "full_name": "Devansh Jain"
    },
    {
        "username": "adhiraj_gupta_2003",
        "full_name": "Adhiraj Gupta"
    },
    {
        "username": "blastonomics",
        "full_name": "Sriram C V"
    },
    {
        "username": "manasvikweera",
        "full_name": "Manasvi Kweera"
    },
    {
        "username": "lakshvant",
        "full_name": "Lakshvant Balachandran"
    },
    {
        "username": "anshuman10_02",
        "full_name": "Anshuman Singh"
    },
    {
        "username": "sujal_k963",
        "full_name": "Sujal Agrawal"
    },
    {
        "username": "saaransh.aggarwal",
        "full_name": "Saaransh Aggarwal"
    },
    {
        "username": "lokesh_m2801",
        "full_name": "Lokesh Mehra"
    },
    {
        "username": "prishita__agrawal",
        "full_name": "Prishita Agrawal"
    },
    {
        "username": "srujan.w",
        "full_name": "Srujan Wadkar"
    },
    {
        "username": "_pushpendra_21",
        "full_name": "Pushpendra Singh"
    },
    {
        "username": "migomiitk",
        "full_name": "Migom"
    },
    {
        "username": "sups_1123",
        "full_name": "Supriya Kumar"
    },
    {
        "username": "sanskar_i_2303",
        "full_name": "Sanskar Yaduka"
    },
    {
        "username": "p_0_g_0",
        "full_name": "Adarsh Anand"
    },
    {
        "username": "geetikag0411",
        "full_name": "Geetika Gupta"
    },
    {
        "username": "aniirbannnn",
        "full_name": ""
    },
    {
        "username": "thandaapani",
        "full_name": "bansod"
    },
    {
        "username": "sowmya_200412",
        "full_name": "Sowmya Thottempudi"
    },
    {
        "username": "anisha_mohapatra6",
        "full_name": "Anisha mohapatra"
    },
    {
        "username": "vasupaliwal31",
        "full_name": "Vasu Paliwal"
    },
    {
        "username": "arnavvgupta_",
        "full_name": "Arnav Gupta"
    },
    {
        "username": "abhishek938kumar",
        "full_name": "Abhishek Kumar"
    },
    {
        "username": "pranay_s22",
        "full_name": "Pranay Saxena"
    },
    {
        "username": "saithepaithewhyyy",
        "full_name": "sai praneeth"
    },
    {
        "username": "shivangagarwal6",
        "full_name": "Shivang Agarwal"
    },
    {
        "username": "i.trip.on.air",
        "full_name": "sagar"
    },
    {
        "username": "shreelock",
        "full_name": "Ajitesh Shree"
    },
    {
        "username": "sar_s321",
        "full_name": "Saraswat S"
    },
    {
        "username": "yaswanth.0.0",
        "full_name": "Yaswanth"
    },
    {
        "username": "yash_gupta0502",
        "full_name": "Yash Gupta"
    },
    {
        "username": "asjad.raza.33",
        "full_name": "Asjad"
    },
    {
        "username": "dhruvv_g21",
        "full_name": "Dhruv Garg"
    },
    {
        "username": "akarshan_saraf_07",
        "full_name": "Akarshan Saraf"
    },
    {
        "username": "sh1vansh.gupta",
        "full_name": "Shivansh Gupta"
    },
    {
        "username": "atharvadeshmukh2003_",
        "full_name": "Atharva Deshmukh"
    },
    {
        "username": "sayeedulislamsheikh",
        "full_name": "Sayeedul Islam Sheikh"
    },
    {
        "username": "anchit_79",
        "full_name": "Anchit Jain"
    },
    {
        "username": "07_partha_c.18",
        "full_name": "Parthapratim Chatterjee"
    },
    {
        "username": "ishanbawne20",
        "full_name": "Ishan Bawne"
    },
    {
        "username": "ojsi_goel",
        "full_name": "Ojsi Goel"
    },
    {
        "username": "saumii_ya",
        "full_name": "Saumya Kanchhal"
    },
    {
        "username": "rikinshah_03",
        "full_name": "Rikin Shah"
    },
    {
        "username": "humanoid_iitk",
        "full_name": "TEAM HUMANOID, IIT KANPUR"
    },
    {
        "username": "siddesh201hazare",
        "full_name": "Siddesh Bharat Hazare"
    },
    {
        "username": "aku_1910",
        "full_name": "Aditya Kulkarni"
    },
    {
        "username": "tasneetsingh",
        "full_name": "Tasneet Singh"
    },
    {
        "username": "_ikartikeya_",
        "full_name": "Kartikeya Gupta"
    },
    {
        "username": "abhishekkhandelwal728",
        "full_name": "Abhishek Khandelwal"
    },
    {
        "username": "maurya73jadav",
        "full_name": "Maurya Jadav"
    },
    {
        "username": "__meenakshi_04_",
        "full_name": "Meenakshi"
    },
    {
        "username": "arca_ane",
        "full_name": "Rahul Jha"
    },
    {
        "username": "zoya_manjer",
        "full_name": "Zoya Manjer"
    },
    {
        "username": "_aditi.17",
        "full_name": "🌸 Aditi 🌸"
    },
    {
        "username": "raw.knuck",
        "full_name": "Raunak Jalan"
    },
    {
        "username": "samyak_singhania",
        "full_name": "Samyak Singhania"
    },
    {
        "username": "tejasahuja_02",
        "full_name": "Tejas Ahuja"
    },
    {
        "username": "emmddxx",
        "full_name": "Emaad Ahmed"
    },
    {
        "username": "rishabh_comrade",
        "full_name": "Rishabh Kumar"
    },
    {
        "username": "era.iitk",
        "full_name": "ERA IITK"
    },
    {
        "username": "pranjalsingh4550",
        "full_name": "Pranjal Singh"
    },
    {
        "username": "ankit_kumar_634",
        "full_name": "Ankit Kumar"
    },
    {
        "username": "_rishi_agarwal_",
        "full_name": "Rishi Agarwal"
    },
    {
        "username": "naman.gpt",
        "full_name": "Naman Gupta"
    },
    {
        "username": "nish.mishh__",
        "full_name": "Nishi Mehta"
    },
    {
        "username": "raman_.03",
        "full_name": "Raman"
    },
    {
        "username": "vision_iitk",
        "full_name": "Team VISiON, IITK"
    },
    {
        "username": "mayankit7",
        "full_name": "Mayankit"
    },
    {
        "username": "akshat_gupta15",
        "full_name": "Akshat Gupta"
    },
    {
        "username": "mridulpandey17",
        "full_name": "Mridul Pandey"
    },
    {
        "username": "sntc_iitmandi",
        "full_name": "Science And Technology Council, IIT Mandi"
    },
    {
        "username": "10_dhruv_07",
        "full_name": "Dhruv Misra"
    },
    {
        "username": "sumitneniwal",
        "full_name": "Sumit Neniwal"
    },
    {
        "username": "lakksi_boi",
        "full_name": "Lakshya Kumar"
    },
    {
        "username": "pradeep_chahal_",
        "full_name": "Pradeep Chahal"
    },
    {
        "username": "prreeemmmmm",
        "full_name": "Prem"
    },
    {
        "username": "ichi.go9087",
        "full_name": ""
    },
    {
        "username": "jaa.namann",
        "full_name": "Naman Jain"
    },
    {
        "username": "_pranavx7_",
        "full_name": "Pranav Ajay Choudhari"
    },
    {
        "username": "khush_g_03",
        "full_name": "Khush Gandhi"
    },
    {
        "username": "ritick_17",
        "full_name": "Ritick"
    },
    {
        "username": "_its_here_mani_",
        "full_name": "×͜× 🅼🅰🅽🅸 ×͜×"
    },
    {
        "username": "on_.the._trail",
        "full_name": "Amal M S"
    },
    {
        "username": "sahil.exe_not_responding",
        "full_name": "Sahil Kumar"
    },
    {
        "username": "iitkms",
        "full_name": "Team IITK Motorsports"
    },
    {
        "username": "samruddhi_1943",
        "full_name": "Samruddhi Lute"
    },
    {
        "username": "sidhant_910",
        "full_name": "Sidhant"
    },
    {
        "username": "hetpatel1705",
        "full_name": "Het Patel"
    },
    {
        "username": "100_ranaway",
        "full_name": "Saubhagya Bawari"
    },
    {
        "username": "keshav.s.a",
        "full_name": "Keshav SA"
    },
    {
        "username": "niles_h_7",
        "full_name": "Nilesh"
    },
    {
        "username": "chinmay_2207",
        "full_name": "Chinmay Pratap"
    },
    {
        "username": "aakarshmishra_1123",
        "full_name": "Aakarsh Mishra"
    },
    {
        "username": "arvind__mehta_",
        "full_name": "Arvind Mehta"
    },
    {
        "username": "niteshkaushal1",
        "full_name": "Nitesh Kaushal"
    },
    {
        "username": "krrish.khandelwal.3",
        "full_name": "Krrish Khandelwal"
    },
    {
        "username": "deepanshu__1809",
        "full_name": "Deepanshü Yadav"
    },
    {
        "username": "anu.shka_02",
        "full_name": "Anushka Gupta"
    },
    {
        "username": "aadarsh_shaw15",
        "full_name": "Aadarsh Shaw"
    },
    {
        "username": "shruti.dalvii",
        "full_name": "Shruti Dalvi"
    },
    {
        "username": "speedcubingiitk",
        "full_name": "SpeedCubing Club IITK"
    },
    {
        "username": "bcs.iitk",
        "full_name": "Brain & Cognitive Society, IIT Kanpur"
    },
    {
        "username": "ayu_raj09",
        "full_name": "Ayush Raj"
    },
    {
        "username": "aayushmaan._",
        "full_name": "Aayushman Gupta"
    },
    {
        "username": "garh_wa_l",
        "full_name": "Nitin Garhwal"
    },
    {
        "username": "suryanshg007",
        "full_name": "Suryansh Goel"
    },
    {
        "username": "bhavna0780",
        "full_name": "Bhavna Jayswal"
    },
    {
        "username": "shivanshuthete",
        "full_name": "Shivanshu Thete"
    },
    {
        "username": "premmilindgujrathi",
        "full_name": "Prem Milind Gujrathi"
    },
    {
        "username": "freddy__512",
        "full_name": "Pradhyumna Lavania"
    },
    {
        "username": "silvrrandbluu",
        "full_name": "sweta"
    },
    {
        "username": "derivative_of_momentum",
        "full_name": "Kaustubh Jha"
    },
    {
        "username": "aadi.tya_5",
        "full_name": "Aditya Gupta"
    },
    {
        "username": "praattsssss",
        "full_name": "Pratibha Bajaj"
    },
    {
        "username": "anand_patwa11",
        "full_name": "Anand Patwa"
    },
    {
        "username": "doesnotexist3002",
        "full_name": "Manjusree Nayak"
    },
    {
        "username": "sajaljain2003",
        "full_name": "Sajal Jain"
    },
    {
        "username": "ishir_roongta",
        "full_name": "Ishir Roongta"
    },
    {
        "username": "yuvrajvasanth",
        "full_name": "Vasanth Yuvraj"
    },
    {
        "username": "k_ujwal_04",
        "full_name": "Ujwal Kumar"
    },
    {
        "username": "aryanxtiwari",
        "full_name": "Aryan Tiwari"
    },
    {
        "username": "__v.shaily__",
        "full_name": "Vaibhav Shaily"
    },
    {
        "username": "devanshirastogi7",
        "full_name": "Devanshi Rastogi"
    },
    {
        "username": "_asn14_the_gr8",
        "full_name": "Ashok Singh Naruka"
    },
    {
        "username": "anushreee_23",
        "full_name": "Anushree Shukla"
    },
    {
        "username": "shruti_kumari1402",
        "full_name": "Shruti Kumari"
    },
    {
        "username": "mr.prakash_abhishek",
        "full_name": "Abhishek Prakash"
    },
    {
        "username": "kschauhan0701",
        "full_name": "Karan Chauhan"
    },
    {
        "username": "vpoojithal",
        "full_name": "Poojitha"
    },
    {
        "username": "_princy_chauhan_",
        "full_name": "Princy Chauhan"
    },
    {
        "username": "haneeswar.16",
        "full_name": "Haneeswar"
    },
    {
        "username": "rts_siller",
        "full_name": "Rajesh Choudhary"
    },
    {
        "username": "rosha_usuratonkachi",
        "full_name": "Roshan Maradana"
    },
    {
        "username": "radhika_24_agrawal_",
        "full_name": "Radhika Agrawal"
    },
    {
        "username": "lakwal__saab",
        "full_name": "𝒩𝒾𝓉𝑒𝓈𝒽 𝒩𝒶𝓀𝓌𝒶𝓁"
    },
    {
        "username": "naman_aggarwal_1",
        "full_name": "Naman Aggarwal"
    },
    {
        "username": "ringsianaman",
        "full_name": "Naman Agarwal"
    },
    {
        "username": "amoghb204",
        "full_name": "Amogh Bhagwat"
    },
    {
        "username": "shubhankar.13_",
        "full_name": "Shubhankar Gambhir"
    },
    {
        "username": "bhuvansingla",
        "full_name": "Bhuvan Singla"
    },
    {
        "username": "roboticsclub_iitk",
        "full_name": "Robotics Club IIT Kanpur"
    },
    {
        "username": "sidpsingh",
        "full_name": "Siddhartha Pratap Singh"
    },
    {
        "username": "hariomvediya",
        "full_name": "Hariom Vediya"
    },
    {
        "username": "akhilagrawal1001",
        "full_name": "Akhil Agrawal"
    },
    {
        "username": "mohit_kul",
        "full_name": "Mohit Kulkarni"
    },
    {
        "username": "virmaldhruv",
        "full_name": "Dhruv Virmal"
    },
    {
        "username": "ashmit__7",
        "full_name": "Ashmit Bathla"
    },
    {
        "username": "ashi__vv30",
        "full_name": "Ashi Vijayvargiya"
    },
    {
        "username": "navyagupta_18",
        "full_name": "navya"
    },
    {
        "username": "abhinaba_iitk",
        "full_name": "Abhinaba Mukherjee"
    },
    {
        "username": "yogit_2003",
        "full_name": "Yogit"
    },
    {
        "username": "navee.1729",
        "full_name": "Navneet Singh"
    },
    {
        "username": "pratyush.gupta.39566",
        "full_name": "Pratyush Gupta"
    },
    {
        "username": "_deepak_adarsh_",
        "full_name": "Deepak Adarsh☺️"
    },
    {
        "username": "pc_jain309",
        "full_name": "Param Veer Choudhary"
    },
    {
        "username": "_agarwal_pv",
        "full_name": "Pavi Agarwal"
    },
    {
        "username": "_vinit10",
        "full_name": "Vinit Toshniwal"
    },
    {
        "username": "sujeet9437",
        "full_name": "Sujeet Kumar"
    },
    {
        "username": "aaiaaitian",
        "full_name": "SHREYANSH"
    },
    {
        "username": "_avi_.gupta._",
        "full_name": "Avi Gupta"
    },
    {
        "username": "heet._.patel",
        "full_name": "Heet Patel"
    },
    {
        "username": "_harsukh_sagri",
        "full_name": "Harsukh Sagri"
    },
    {
        "username": "devansh_jain2013",
        "full_name": "Devansh Jain"
    },
    {
        "username": "_sid_wat_",
        "full_name": "Sidhartha Watsa"
    },
    {
        "username": "_gagan._.19",
        "full_name": "Gagandeep Kolambe"
    },
    {
        "username": "ynikhil_28",
        "full_name": "Nikhil Yadav"
    },
    {
        "username": "jhajayant_1109",
        "full_name": "Jayant Jha"
    },
    {
        "username": "anirudh_xxv",
        "full_name": "Anirudh Meena"
    },
    {
        "username": "omshrivastava36",
        "full_name": "Om Shrivastava"
    },
    {
        "username": "avinash.not.found",
        "full_name": "🍫𝐀νⓘή𝐚ŞĤ ҜᵘⓂᵃŘ  ⁠♡"
    },
    {
        "username": "_.vishal_03._",
        "full_name": "Vishal Himmatsinghka"
    },
    {
        "username": "mohammad__suhail_",
        "full_name": "محمد سہیل"
    },
    {
        "username": "ak_212__",
        "full_name": "Akash Kumar"
    },
    {
        "username": "utkarsh_kandi",
        "full_name": "Utkarsh Kandi"
    },
    {
        "username": "asifnawaz18876",
        "full_name": "Asif Nawaz"
    },
    {
        "username": "piyushraj___",
        "full_name": "P I Y U S H 🍁"
    },
    {
        "username": "shubh.agrawal10",
        "full_name": "Shubh Agrawal"
    },
    {
        "username": "nearly_headless_",
        "full_name": "Shreya Rajak"
    },
    {
        "username": "sikarwarbhavya",
        "full_name": "Bhavya Sikarwar"
    },
    {
        "username": "jivnani_harshal",
        "full_name": "Harshal Jivnani"
    },
    {
        "username": "1prthm_srvstv",
        "full_name": "Pratham Srivastava"
    },
    {
        "username": "_vipulchanchlani_",
        "full_name": "Vipul Chanchlani"
    },
    {
        "username": "sanyam_919",
        "full_name": "Sanyam Singla"
    },
    {
        "username": "chitwan982",
        "full_name": "Chitwan"
    },
    {
        "username": "chetanya_goenka",
        "full_name": "Chetanya Goenka"
    },
    {
        "username": "ananya0102_",
        "full_name": "Ananya Mehrotra"
    },
    {
        "username": "sarthakagrwl",
        "full_name": "Sarthak Agarwal"
    },
    {
        "username": "prakharpratapmall",
        "full_name": "Prakhar Pratap Mall"
    },
    {
        "username": "_akshu.jain_",
        "full_name": "Akshat Jain"
    },
    {
        "username": "anchit_373",
        "full_name": "Anchit Gupta"
    },
    {
        "username": "dakshitam_",
        "full_name": "Dakshita Mittal"
    },
    {
        "username": "_daxal_p",
        "full_name": "Daxal P"
    },
    {
        "username": "smoky_utkarsh",
        "full_name": "Utkarsh Gupta"
    },
    {
        "username": "nithinnallani",
        "full_name": "Nithin Nallani"
    },
    {
        "username": "rastogij22",
        "full_name": "Jatin Rastogi"
    },
    {
        "username": "sanyam_pasricha",
        "full_name": "Sanyam Pasricha"
    },
    {
        "username": "nishanth._.02",
        "full_name": "Nishanth Shanmukham"
    },
    {
        "username": "vibhansh_bhatia",
        "full_name": "Vibhansh Bhatia"
    },
    {
        "username": "archit_182",
        "full_name": "Archit Agarwal"
    },
    {
        "username": "sujal_harkut",
        "full_name": "Sujal Harkut"
    },
    {
        "username": "sahil.void",
        "full_name": "Sahil Singh"
    },
    {
        "username": "prem.bharwani",
        "full_name": "Prem Bharwani"
    },
    {
        "username": "iitkconsult",
        "full_name": "IIT Kanpur Consulting Group"
    },
    {
        "username": "pclubiitk",
        "full_name": "Programming Club, IIT Kanpur"
    },
    {
        "username": "igarimamittal",
        "full_name": "Garima Mittal"
    },
    {
        "username": "_shreyanshagarwal_",
        "full_name": "Shreyansh Agarwal"
    },
    {
        "username": "luhhvesh",
        "full_name": "Lavesh Gupta"
    },
    {
        "username": "mukesh_siddh_iitk",
        "full_name": "Mukesh_siddh21"
    },
    {
        "username": "kritnandan2",
        "full_name": "kritnandan"
    },
    {
        "username": "utkarshaditya21",
        "full_name": "Utkarsh Aditya"
    },
    {
        "username": "khokar_adit",
        "full_name": "Adit Khokar"
    },
    {
        "username": "ronit__agarwal",
        "full_name": "Ronit Agarwal"
    },
    {
        "username": "khandelwalkhush05",
        "full_name": "Khush Khandelwal"
    },
    {
        "username": "_shrutidalal_",
        "full_name": "Shruti Dalal"
    },
    {
        "username": "_saadist_",
        "full_name": "Mohammad Saad"
    },
    {
        "username": "voyager10_01",
        "full_name": "Parth Srivastava"
    },
    {
        "username": "aniruddh.pramod",
        "full_name": "Aniruddh Pramod"
    },
    {
        "username": "alka.1308",
        "full_name": "Alka Aggarwal"
    },
    {
        "username": "pankajh.j",
        "full_name": "Pankajh Jhamtani"
    },
    {
        "username": "arnav_pandey007",
        "full_name": "ARNAV PANDEY"
    },
    {
        "username": "utkarsh7u",
        "full_name": "Utkarsh Kumar"
    },
    {
        "username": "saur.aaabh",
        "full_name": "Saurabh Patil"
    },
    {
        "username": "astroclub.iitk",
        "full_name": "Astronomy Club, IIT Kanpur"
    },
    {
        "username": "mercapt4758",
        "full_name": "mercapt4758L"
    },
    {
        "username": "prakkhar.mishra",
        "full_name": "Prakhar Mishra"
    },
    {
        "username": "_nikita._.25",
        "full_name": "Nikita Singh"
    },
    {
        "username": "_om.elette",
        "full_name": "Om Jee"
    },
    {
        "username": "i_am_ashish.pvt",
        "full_name": "Ashish Gautam"
    },
    {
        "username": "atulgupta2510",
        "full_name": "Atul Gupta"
    },
    {
        "username": "rudransh._",
        "full_name": "Rudransh Gupta"
    },
    {
        "username": "gamedev_iitk",
        "full_name": "Game Development Club, IIT Kanpur"
    },
    {
        "username": "adi_palmate_7",
        "full_name": "Aditya"
    },
    {
        "username": "aero_club_iitk",
        "full_name": "Aeromodelling Club, IIT Kanpur"
    },
    {
        "username": "fac.iitk",
        "full_name": "Finance and Analytics Club"
    },
    {
        "username": "madhav_921",
        "full_name": "Madhav P"
    },
    {
        "username": "adityaanand28",
        "full_name": "Aditya Anand"
    },
    {
        "username": "p.s.ingh02",
        "full_name": "Prabuddha Singh"
    },
    {
        "username": "som.tambe",
        "full_name": "Som Tambe"
    }
]
